{
  "display": {
    "icon": {
      "item": "sinocraft:knife"
    },
    "title": {
      "translate": "advancement.sinocraft.basic.get_bark.title"
    },
    "description": {
      "translate": "advancement.sinocraft.basic.get_bark.description"
    },
    "frame": "task",
    "show_toast": true,
    "announce_to_chat": true,
    "hidden": false
  },
  "parent": "sinocraft:basic/knife",
  "criteria": {
    "use_knife": {
      "trigger": "sinocraft:shave_bark_with_knife",
      "conditions": {}
    }
  },
  "requirements": [
    [
      "use_knife"
    ]
  ],
  "rewards": {}
}