{
  "display": {
    "icon": {
      "item": "sinocraft:white_marble"
    },
    "title": {
      "translate": "advancement.sinocraft.basic.root.title"
    },
    "description": {
      "translate": "advancement.sinocraft.basic.root.description"
    },
    "frame": "task",
    "background": "sinocraft:textures/gui/advancements/backgrounds/white_marble.png",
    "show_toast": false,
    "announce_to_chat": true,
    "hidden": false
  },
  "criteria": {
    "only": {
      "trigger": "minecraft:tick"
    }
  },
  "requirements": [
    [
      "only"
    ]
  ],
  "rewards": {}
}